{
  "photo_path": "/Volumes/SDCARD/photo/calibration/calibration_y-1p-10r3.jpg",
  "filename": "calibration_y-1p-10r3.jpg",
  "timestamp": "2026-05-06T06:16:37.367074",
  "parsed_year": null,
  "image_width": 1200,
  "image_height": 1200,
  "image_format": "JPEG",
  "image_mode": "RGB",
  "pose_yaw": 2.044,
  "pose_pitch": 12.5643,
  "pose_roll": -2.4323,
  "pose_source": "3ddfa",
  "pose_classification": "frontal",
  "bbox_x": 244.0,
  "bbox_y": 305.0,
  "bbox_w": 665.0,
  "bbox_h": 815.0,
  "bbox_score": 1.0,
  "bbox_kp5": [],
  "face_mean_lum": 132.1557,
  "face_std_lum": 51.7613,
  "face_mean_r": 168.0029,
  "face_mean_g": 122.9644,
  "face_mean_b": 105.4997,
  "face_std_r": 38.8581,
  "face_std_g": 48.1344,
  "face_std_b": 46.1604,
  "quality_blur": 738.5468,
  "quality_sharpness": 738.5468,
  "quality_jpeg": 3.4391,
  "quality_overall": 0.8624,
  "reconstruction_success": true,
  "vertices_count": 35709,
  "triangles_count": 70789,
  "mesh_path": "/Volumes/SDCARD/storage/calibration/calibration_y-1p-10r3",
  "uv_texture_path": "/Volumes/SDCARD/storage/calibration/calibration_y-1p-10r3/uv_texture_hd.jpg",
  "uv_confidence_mask_path": "/Volumes/SDCARD/storage/calibration/calibration_y-1p-10r3/uv_confidence_mask.jpg",
  "segmented_face_path": "/Volumes/SDCARD/storage/calibration/calibration_y-1p-10r3/face_crop.png",
  "texture_predictions": {
    "lbp_complexity": 3.0978,
    "lbp_uniformity": 0.6847,
    "specular_gloss": 0.8784,
    "silicone_probability": 0.5795,
    "raw_silicone_probability": 0.6439,
    "reliability_weight": 0.5381,
    "pore_density": 0.0517,
    "spot_density": 0.0612,
    "wrinkle_forehead": 141.178,
    "wrinkle_nasolabial": 1.197,
    "albedo_uniformity": 0.9077,
    "global_smoothness": 0.6011,
    "studio_lighting_score": 0.0,
    "retouch_score": 0.25,
    "quality": {
      "quality_index": 0.6385,
      "sharpness_score": 0.9411,
      "jpeg_score": 0.0,
      "noise_score": 0.8735,
      "laplacian_var": 470.559,
      "blockiness": 48.9496,
      "noise_level": 1.2647
    }
  },
  "texture_actual": {},
  "texture_analysis_notes": [],
  "geometric_metrics": {
    "cranial_face_index": 0.6024,
    "jaw_width_ratio": 0.1769,
    "canthal_tilt_L": -9.6218,
    "canthal_tilt_R": -0.3633,
    "interorbital_ratio": 0.7389,
    "orbit_depth_L_ratio": 0.2298,
    "orbit_depth_R_ratio": 0.2363,
    "gonial_angle_L": 56.1014,
    "gonial_angle_R": 42.3268,
    "mandibular_ramus_length": 0.5738,
    "nose_width_ratio": 0.1881,
    "nose_projection_ratio": 0.4658,
    "nasal_frontal_index": 0.2078,
    "chin_projection_ratio": 0.1383,
    "orbit_centroid_ratio": 0.5294,
    "forehead_slope_index": 0.0617,
    "nasofacial_angle_ratio": 0.2806,
    "orbital_asymmetry_index": 0.0064,
    "chin_offset_asymmetry": 0.4538
  },
  "errors": [],
  "bucket": "frontal",
  "pose_bucket": "frontal",
  "bucket_ui": "frontal",
  "status": "ready",
  "reliability_weight": 1.0,
  "expression": {
    "mouth_open_intensity": 0.3196,
    "smile_intensity": 1.8039,
    "is_mouth_open_detected": true,
    "is_smile_detected": true
  },
  "metrics": {
    "cranial_face_index": 0.6024,
    "jaw_width_ratio": 0.1769,
    "canthal_tilt_L": -9.6218,
    "canthal_tilt_R": -0.3633,
    "interorbital_ratio": 0.7389,
    "orbit_depth_L_ratio": 0.2298,
    "orbit_depth_R_ratio": 0.2363,
    "gonial_angle_L": 56.1014,
    "gonial_angle_R": 42.3268,
    "mandibular_ramus_length": 0.5738,
    "nose_width_ratio": 0.1881,
    "nose_projection_ratio": 0.4658,
    "nasal_frontal_index": 0.2078,
    "chin_projection_ratio": 0.1383,
    "orbit_centroid_ratio": 0.5294,
    "forehead_slope_index": 0.0617,
    "nasofacial_angle_ratio": 0.2806,
    "orbital_asymmetry_index": 0.0064,
    "chin_offset_asymmetry": 0.4538,
    "texture_studio_lighting": 0.0,
    "texture_retouch": 0.25,
    "texture_lbp_complexity": 3.0978,
    "texture_specular_gloss": 0.8784,
    "texture_spot_density": 0.0612,
    "texture_wrinkle_forehead": 141.178
  },
  "bucket_metrics_coverage": 0.84
}